<?xml version="1.0" encoding="utf-8" standalone="yes"?>
<Overwatch_Memory_Cell Size="90">
  <Moment Index="0" Time="0">
    <Info>
      <Scholar Id="0" Type="Scholar">
        <Position>
          <X>95</X>
          <Y>17.450592</Y>
        </Position>
        <Rotation>0</Rotation>
      </Scholar>
    </Info>
  </Moment>
  <Moment Index="1" Time="0">
    <Info>
      <Scholar Id="0" Type="Scholar">
        <Position>
          <X>95</X>
          <Y>17.3386269</Y>
        </Position>
        <Rotation>0</Rotation>
      </Scholar>
    </Info>
  </Moment>
  <Moment Index="2" Time="0">
    <Info>
      <Scholar Id="0" Type="Scholar">
        <Position>
          <X>95</X>
          <Y>17.2810421</Y>
        </Position>
        <Rotation>0</Rotation>
      </Scholar>
    </Info>
  </Moment>
  <Moment Index="3" Time="0">
    <Info>
      <Scholar Id="0" Type="Scholar">
        <Position>
          <X>95</X>
          <Y>17.2176781</Y>
        </Position>
        <Rotation>0</Rotation>
      </Scholar>
    </Info>
  </Moment>
  <Moment Index="4" Time="0">
    <Info>
      <Scholar Id="0" Type="Scholar">
        <Position>
          <X>95</X>
          <Y>17.1840916</Y>
        </Position>
        <Rotation>0</Rotation>
      </Scholar>
    </Info>
  </Moment>
  <Moment Index="5" Time="0">
    <Info>
      <Scholar Id="0" Type="Scholar">
        <Position>
          <X>95</X>
          <Y>17.0391045</Y>
        </Position>
        <Rotation>0</Rotation>
      </Scholar>
    </Info>
  </Moment>
  <Moment Index="6" Time="0">
    <Info>
      <Scholar Id="0" Type="Scholar">
        <Position>
          <X>95</X>
          <Y>16.9612713</Y>
        </Position>
        <Rotation>0</Rotation>
      </Scholar>
    </Info>
  </Moment>
  <Moment Index="7" Time="0">
    <Info>
      <Scholar Id="0" Type="Scholar">
        <Position>
          <X>95</X>
          <Y>16.8805485</Y>
        </Position>
        <Rotation>0</Rotation>
      </Scholar>
    </Info>
  </Moment>
  <Moment Index="8" Time="0">
    <Info>
      <Scholar Id="0" Type="Scholar">
        <Position>
          <X>95</X>
          <Y>16.7549286</Y>
        </Position>
        <Rotation>0</Rotation>
      </Scholar>
    </Info>
  </Moment>
  <Moment Index="9" Time="0">
    <Info>
      <Scholar Id="0" Type="Scholar">
        <Position>
          <X>95</X>
          <Y>16.6686554</Y>
        </Position>
        <Rotation>0</Rotation>
      </Scholar>
    </Info>
  </Moment>
  <Moment Index="10" Time="0">
    <Info>
      <Scholar Id="0" Type="Scholar">
        <Position>
          <X>95</X>
          <Y>16.5806942</Y>
        </Position>
        <Rotation>0</Rotation>
      </Scholar>
    </Info>
  </Moment>
  <Moment Index="11" Time="0">
    <Info>
      <Scholar Id="0" Type="Scholar">
        <Position>
          <X>95</X>
          <Y>16.4912872</Y>
        </Position>
        <Rotation>0</Rotation>
      </Scholar>
    </Info>
  </Moment>
  <Moment Index="12" Time="0">
    <Info>
      <Scholar Id="0" Type="Scholar">
        <Position>
          <X>95</X>
          <Y>16.3549061</Y>
        </Position>
        <Rotation>0</Rotation>
      </Scholar>
    </Info>
  </Moment>
  <Moment Index="13" Time="0">
    <Info>
      <Scholar Id="0" Type="Scholar">
        <Position>
          <X>95</X>
          <Y>16.262722</Y>
        </Position>
        <Rotation>0</Rotation>
      </Scholar>
    </Info>
  </Moment>
  <Moment Index="14" Time="0">
    <Info>
      <Scholar Id="0" Type="Scholar">
        <Position>
          <X>95</X>
          <Y>16.169693</Y>
        </Position>
        <Rotation>0</Rotation>
      </Scholar>
    </Info>
  </Moment>
  <Moment Index="15" Time="0">
    <Info>
      <Scholar Id="0" Type="Scholar">
        <Position>
          <X>95</X>
          <Y>16.0759411</Y>
        </Position>
        <Rotation>0</Rotation>
      </Scholar>
    </Info>
  </Moment>
  <Moment Index="16" Time="0">
    <Info>
      <Scholar Id="0" Type="Scholar">
        <Position>
          <X>95</X>
          <Y>15.93418</Y>
        </Position>
        <Rotation>0</Rotation>
      </Scholar>
    </Info>
  </Moment>
  <Moment Index="17" Time="0">
    <Info>
      <Scholar Id="0" Type="Scholar">
        <Position>
          <X>95</X>
          <Y>15.83904</Y>
        </Position>
        <Rotation>0</Rotation>
      </Scholar>
    </Info>
  </Moment>
  <Moment Index="18" Time="0">
    <Info>
      <Scholar Id="0" Type="Scholar">
        <Position>
          <X>95</X>
          <Y>15.7434769</Y>
        </Position>
        <Rotation>0</Rotation>
      </Scholar>
    </Info>
  </Moment>
  <Moment Index="19" Time="1">
    <Info>
      <Scholar Id="0" Type="Scholar">
        <Position>
          <X>95</X>
          <Y>15.5994711</Y>
        </Position>
        <Rotation>0</Rotation>
      </Scholar>
    </Info>
  </Moment>
  <Moment Index="20" Time="1">
    <Info>
      <Scholar Id="0" Type="Scholar">
        <Position>
          <X>95</X>
          <Y>15.5030985</Y>
        </Position>
        <Rotation>0</Rotation>
      </Scholar>
    </Info>
  </Moment>
  <Moment Index="21" Time="1">
    <Info>
      <Scholar Id="0" Type="Scholar">
        <Position>
          <X>95</X>
          <Y>15.4064789</Y>
        </Position>
        <Rotation>0</Rotation>
      </Scholar>
    </Info>
  </Moment>
  <Moment Index="22" Time="1">
    <Info>
      <Scholar Id="0" Type="Scholar">
        <Position>
          <X>95</X>
          <Y>15.2611628</Y>
        </Position>
        <Rotation>0</Rotation>
      </Scholar>
    </Info>
  </Moment>
  <Moment Index="23" Time="1">
    <Info>
      <Scholar Id="0" Type="Scholar">
        <Position>
          <X>95</X>
          <Y>15.16407</Y>
        </Position>
        <Rotation>0</Rotation>
      </Scholar>
    </Info>
  </Moment>
  <Moment Index="24" Time="1">
    <Info>
      <Scholar Id="0" Type="Scholar">
        <Position>
          <X>95</X>
          <Y>15.0668344</Y>
        </Position>
        <Rotation>0</Rotation>
      </Scholar>
    </Info>
  </Moment>
  <Moment Index="25" Time="1">
    <Info>
      <Scholar Id="0" Type="Scholar">
        <Position>
          <X>95</X>
          <Y>14.9694757</Y>
        </Position>
        <Rotation>0</Rotation>
      </Scholar>
    </Info>
  </Moment>
  <Moment Index="26" Time="1">
    <Info>
      <Scholar Id="0" Type="Scholar">
        <Position>
          <X>95</X>
          <Y>14.87201</Y>
        </Position>
        <Rotation>0</Rotation>
      </Scholar>
    </Info>
  </Moment>
  <Moment Index="27" Time="1">
    <Info>
      <Scholar Id="0" Type="Scholar">
        <Position>
          <X>95</X>
          <Y>14.725647</Y>
        </Position>
        <Rotation>0</Rotation>
      </Scholar>
    </Info>
  </Moment>
  <Moment Index="28" Time="1">
    <Info>
      <Scholar Id="0" Type="Scholar">
        <Position>
          <X>95</X>
          <Y>14.6279793</Y>
        </Position>
        <Rotation>0</Rotation>
      </Scholar>
    </Info>
  </Moment>
  <Moment Index="29" Time="1">
    <Info>
      <Scholar Id="0" Type="Scholar">
        <Position>
          <X>95</X>
          <Y>14.53025</Y>
        </Position>
        <Rotation>0</Rotation>
      </Scholar>
    </Info>
  </Moment>
  <Moment Index="30" Time="1">
    <Info>
      <Scholar Id="0" Type="Scholar">
        <Position>
          <X>95</X>
          <Y>14.4324675</Y>
        </Position>
        <Rotation>0</Rotation>
      </Scholar>
    </Info>
  </Moment>
  <Moment Index="31" Time="1">
    <Info>
      <Scholar Id="0" Type="Scholar">
        <Position>
          <X>95</X>
          <Y>14.3346405</Y>
        </Position>
        <Rotation>0</Rotation>
      </Scholar>
    </Info>
  </Moment>
  <Moment Index="32" Time="1">
    <Info>
      <Scholar Id="0" Type="Scholar">
        <Position>
          <X>95</X>
          <Y>14.1878271</Y>
        </Position>
        <Rotation>0</Rotation>
      </Scholar>
    </Info>
  </Moment>
  <Moment Index="33" Time="1">
    <Info>
      <Scholar Id="0" Type="Scholar">
        <Position>
          <X>95</X>
          <Y>14.0899124</Y>
        </Position>
        <Rotation>0</Rotation>
      </Scholar>
    </Info>
  </Moment>
  <Moment Index="34" Time="1">
    <Info>
      <Scholar Id="0" Type="Scholar">
        <Position>
          <X>95</X>
          <Y>13.991971</Y>
        </Position>
        <Rotation>0</Rotation>
      </Scholar>
    </Info>
  </Moment>
  <Moment Index="35" Time="1">
    <Info>
      <Scholar Id="0" Type="Scholar">
        <Position>
          <X>95</X>
          <Y>13.8940077</Y>
        </Position>
        <Rotation>0</Rotation>
      </Scholar>
    </Info>
  </Moment>
  <Moment Index="36" Time="1">
    <Info>
      <Scholar Id="0" Type="Scholar">
        <Position>
          <X>95</X>
          <Y>13.7470264</Y>
        </Position>
        <Rotation>0</Rotation>
      </Scholar>
    </Info>
  </Moment>
  <Moment Index="37" Time="1">
    <Info>
      <Scholar Id="0" Type="Scholar">
        <Position>
          <X>95</X>
          <Y>13.6490192</Y>
        </Position>
        <Rotation>0</Rotation>
      </Scholar>
    </Info>
  </Moment>
  <Moment Index="38" Time="1">
    <Info>
      <Scholar Id="0" Type="Scholar">
        <Position>
          <X>95</X>
          <Y>13.5509987</Y>
        </Position>
        <Rotation>0</Rotation>
      </Scholar>
    </Info>
  </Moment>
  <Moment Index="39" Time="1">
    <Info>
      <Scholar Id="0" Type="Scholar">
        <Position>
          <X>95</X>
          <Y>13.4039469</Y>
        </Position>
        <Rotation>0</Rotation>
      </Scholar>
    </Info>
  </Moment>
  <Moment Index="40" Time="1">
    <Info>
      <Scholar Id="0" Type="Scholar">
        <Position>
          <X>95</X>
          <Y>13.3059015</Y>
        </Position>
        <Rotation>0</Rotation>
      </Scholar>
    </Info>
  </Moment>
  <Moment Index="41" Time="2">
    <Info>
      <Scholar Id="0" Type="Scholar">
        <Position>
          <X>95</X>
          <Y>13.2078485</Y>
        </Position>
        <Rotation>0</Rotation>
      </Scholar>
    </Info>
  </Moment>
  <Moment Index="42" Time="2">
    <Info>
      <Scholar Id="0" Type="Scholar">
        <Position>
          <X>95</X>
          <Y>13.1588192</Y>
        </Position>
        <Rotation>0</Rotation>
      </Scholar>
    </Info>
  </Moment>
  <Moment Index="43" Time="2">
    <Info>
      <Scholar Id="0" Type="Scholar">
        <Position>
          <X>95</X>
          <Y>13.0117226</Y>
        </Position>
        <Rotation>0</Rotation>
      </Scholar>
    </Info>
  </Moment>
  <Moment Index="44" Time="2">
    <Info>
      <Scholar Id="0" Type="Scholar">
        <Position>
          <X>95</X>
          <Y>12.9136515</Y>
        </Position>
        <Rotation>0</Rotation>
      </Scholar>
    </Info>
  </Moment>
  <Moment Index="45" Time="2">
    <Info>
      <Scholar Id="0" Type="Scholar">
        <Position>
          <X>95</X>
          <Y>12.8155766</Y>
        </Position>
        <Rotation>0</Rotation>
      </Scholar>
    </Info>
  </Moment>
  <Moment Index="46" Time="2">
    <Info>
      <Scholar Id="0" Type="Scholar">
        <Position>
          <X>95</X>
          <Y>12.7174978</Y>
        </Position>
        <Rotation>0</Rotation>
      </Scholar>
    </Info>
  </Moment>
  <Moment Index="47" Time="2">
    <Info>
      <Scholar Id="0" Type="Scholar">
        <Position>
          <X>95</X>
          <Y>12.5703745</Y>
        </Position>
        <Rotation>0</Rotation>
      </Scholar>
    </Info>
  </Moment>
  <Moment Index="48" Time="2">
    <Info>
      <Scholar Id="0" Type="Scholar">
        <Position>
          <X>95</X>
          <Y>12.4722891</Y>
        </Position>
        <Rotation>0</Rotation>
      </Scholar>
    </Info>
  </Moment>
  <Moment Index="49" Time="2">
    <Info>
      <Scholar Id="0" Type="Scholar">
        <Position>
          <X>95</X>
          <Y>12.3742018</Y>
        </Position>
        <Rotation>0</Rotation>
      </Scholar>
    </Info>
  </Moment>
  <Moment Index="50" Time="2">
    <Info>
      <Scholar Id="0" Type="Scholar">
        <Position>
          <X>95</X>
          <Y>12.227067</Y>
        </Position>
        <Rotation>0</Rotation>
      </Scholar>
    </Info>
  </Moment>
  <Moment Index="51" Time="2">
    <Info>
      <Scholar Id="0" Type="Scholar">
        <Position>
          <X>95</X>
          <Y>12.1289759</Y>
        </Position>
        <Rotation>0</Rotation>
      </Scholar>
    </Info>
  </Moment>
  <Moment Index="52" Time="2">
    <Info>
      <Scholar Id="0" Type="Scholar">
        <Position>
          <X>95</X>
          <Y>12.0308828</Y>
        </Position>
        <Rotation>0</Rotation>
      </Scholar>
    </Info>
  </Moment>
  <Moment Index="53" Time="2">
    <Info>
      <Scholar Id="0" Type="Scholar">
        <Position>
          <X>95</X>
          <Y>11.93279</Y>
        </Position>
        <Rotation>0</Rotation>
      </Scholar>
    </Info>
  </Moment>
  <Moment Index="54" Time="2">
    <Info>
      <Scholar Id="0" Type="Scholar">
        <Position>
          <X>95</X>
          <Y>11.8346949</Y>
        </Position>
        <Rotation>0</Rotation>
      </Scholar>
    </Info>
  </Moment>
  <Moment Index="55" Time="2">
    <Info>
      <Scholar Id="0" Type="Scholar">
        <Position>
          <X>95</X>
          <Y>11.6875525</Y>
        </Position>
        <Rotation>0</Rotation>
      </Scholar>
    </Info>
  </Moment>
  <Moment Index="56" Time="2">
    <Info>
      <Scholar Id="0" Type="Scholar">
        <Position>
          <X>95</X>
          <Y>11.5894556</Y>
        </Position>
        <Rotation>0</Rotation>
      </Scholar>
    </Info>
  </Moment>
  <Moment Index="57" Time="2">
    <Info>
      <Scholar Id="0" Type="Scholar">
        <Position>
          <X>95</X>
          <Y>11.4913588</Y>
        </Position>
        <Rotation>0</Rotation>
      </Scholar>
    </Info>
  </Moment>
  <Moment Index="58" Time="2">
    <Info>
      <Scholar Id="0" Type="Scholar">
        <Position>
          <X>95</X>
          <Y>11.3932619</Y>
        </Position>
        <Rotation>0</Rotation>
      </Scholar>
    </Info>
  </Moment>
  <Moment Index="59" Time="2">
    <Info>
      <Scholar Id="0" Type="Scholar">
        <Position>
          <X>95</X>
          <Y>11.2461157</Y>
        </Position>
        <Rotation>0</Rotation>
      </Scholar>
    </Info>
  </Moment>
  <Moment Index="60" Time="2">
    <Info>
      <Scholar Id="0" Type="Scholar">
        <Position>
          <X>95</X>
          <Y>11.1970663</Y>
        </Position>
        <Rotation>0</Rotation>
      </Scholar>
    </Info>
  </Moment>
  <Moment Index="61" Time="2">
    <Info>
      <Scholar Id="0" Type="Scholar">
        <Position>
          <X>95</X>
          <Y>11.0499182</Y>
        </Position>
        <Rotation>0</Rotation>
      </Scholar>
    </Info>
  </Moment>
  <Moment Index="62" Time="2">
    <Info>
      <Scholar Id="0" Type="Scholar">
        <Position>
          <X>95</X>
          <Y>10.9518194</Y>
        </Position>
        <Rotation>0</Rotation>
      </Scholar>
    </Info>
  </Moment>
  <Moment Index="63" Time="2">
    <Info>
      <Scholar Id="0" Type="Scholar">
        <Position>
          <X>95</X>
          <Y>10.8537207</Y>
        </Position>
        <Rotation>0</Rotation>
      </Scholar>
    </Info>
  </Moment>
  <Moment Index="64" Time="3">
    <Info>
      <Scholar Id="0" Type="Scholar">
        <Position>
          <X>95</X>
          <Y>10.7556219</Y>
        </Position>
        <Rotation>0</Rotation>
      </Scholar>
    </Info>
  </Moment>
  <Moment Index="65" Time="3">
    <Info>
      <Scholar Id="0" Type="Scholar">
        <Position>
          <X>95</X>
          <Y>10.6084738</Y>
        </Position>
        <Rotation>0</Rotation>
      </Scholar>
    </Info>
  </Moment>
  <Moment Index="66" Time="3">
    <Info>
      <Scholar Id="0" Type="Scholar">
        <Position>
          <X>95</X>
          <Y>10.510375</Y>
        </Position>
        <Rotation>0</Rotation>
      </Scholar>
    </Info>
  </Moment>
  <Moment Index="67" Time="3">
    <Info>
      <Scholar Id="0" Type="Scholar">
        <Position>
          <X>95</X>
          <Y>10.4122763</Y>
        </Position>
        <Rotation>0</Rotation>
      </Scholar>
    </Info>
  </Moment>
  <Moment Index="68" Time="3">
    <Info>
      <Scholar Id="0" Type="Scholar">
        <Position>
          <X>95</X>
          <Y>10.3141775</Y>
        </Position>
        <Rotation>0</Rotation>
      </Scholar>
    </Info>
  </Moment>
  <Moment Index="69" Time="3">
    <Info>
      <Scholar Id="0" Type="Scholar">
        <Position>
          <X>95</X>
          <Y>10.1670294</Y>
        </Position>
        <Rotation>0</Rotation>
      </Scholar>
    </Info>
  </Moment>
  <Moment Index="70" Time="3">
    <Info>
      <Scholar Id="0" Type="Scholar">
        <Position>
          <X>95</X>
          <Y>10.0689306</Y>
        </Position>
        <Rotation>0</Rotation>
      </Scholar>
    </Info>
  </Moment>
  <Moment Index="71" Time="3">
    <Info>
      <Scholar Id="0" Type="Scholar">
        <Position>
          <X>95</X>
          <Y>9.970832</Y>
        </Position>
        <Rotation>0</Rotation>
      </Scholar>
    </Info>
  </Moment>
  <Moment Index="72" Time="3">
    <Info>
      <Scholar Id="0" Type="Scholar">
        <Position>
          <X>95</X>
          <Y>9.872733</Y>
        </Position>
        <Rotation>0</Rotation>
      </Scholar>
    </Info>
  </Moment>
  <Moment Index="73" Time="3">
    <Info>
      <Scholar Id="0" Type="Scholar">
        <Position>
          <X>95</X>
          <Y>9.774633</Y>
        </Position>
        <Rotation>0</Rotation>
      </Scholar>
    </Info>
  </Moment>
  <Moment Index="74" Time="3">
    <Info>
      <Scholar Id="0" Type="Scholar">
        <Position>
          <X>95</X>
          <Y>9.676533</Y>
        </Position>
        <Rotation>0</Rotation>
      </Scholar>
    </Info>
  </Moment>
  <Moment Index="75" Time="3">
    <Info>
      <Scholar Id="0" Type="Scholar">
        <Position>
          <X>95</X>
          <Y>9.529382</Y>
        </Position>
        <Rotation>0</Rotation>
      </Scholar>
    </Info>
  </Moment>
  <Moment Index="76" Time="3">
    <Info>
      <Scholar Id="0" Type="Scholar">
        <Position>
          <X>95</X>
          <Y>9.431281</Y>
        </Position>
        <Rotation>0</Rotation>
      </Scholar>
    </Info>
  </Moment>
  <Moment Index="77" Time="3">
    <Info>
      <Scholar Id="0" Type="Scholar">
        <Position>
          <X>95</X>
          <Y>9.33318</Y>
        </Position>
        <Rotation>0</Rotation>
      </Scholar>
    </Info>
  </Moment>
  <Moment Index="78" Time="3">
    <Info>
      <Scholar Id="0" Type="Scholar">
        <Position>
          <X>95</X>
          <Y>9.23508</Y>
        </Position>
        <Rotation>0</Rotation>
      </Scholar>
    </Info>
  </Moment>
  <Moment Index="79" Time="3">
    <Info>
      <Scholar Id="0" Type="Scholar">
        <Position>
          <X>95</X>
          <Y>9.136979</Y>
        </Position>
        <Rotation>0</Rotation>
      </Scholar>
    </Info>
  </Moment>
  <Moment Index="80" Time="3">
    <Info>
      <Scholar Id="0" Type="Scholar">
        <Position>
          <X>95</X>
          <Y>9.038878</Y>
        </Position>
        <Rotation>0</Rotation>
      </Scholar>
    </Info>
  </Moment>
  <Moment Index="81" Time="3">
    <Info>
      <Scholar Id="0" Type="Scholar">
        <Position>
          <X>95</X>
          <Y>8.891727</Y>
        </Position>
        <Rotation>0</Rotation>
      </Scholar>
    </Info>
  </Moment>
  <Moment Index="82" Time="3">
    <Info>
      <Scholar Id="0" Type="Scholar">
        <Position>
          <X>95</X>
          <Y>8.793627</Y>
        </Position>
        <Rotation>0</Rotation>
      </Scholar>
    </Info>
  </Moment>
  <Moment Index="83" Time="3">
    <Info>
      <Scholar Id="0" Type="Scholar">
        <Position>
          <X>95</X>
          <Y>8.695526</Y>
        </Position>
        <Rotation>0</Rotation>
      </Scholar>
    </Info>
  </Moment>
  <Moment Index="84" Time="3">
    <Info>
      <Scholar Id="0" Type="Scholar">
        <Position>
          <X>95</X>
          <Y>8.597425</Y>
        </Position>
        <Rotation>0</Rotation>
      </Scholar>
    </Info>
  </Moment>
  <Moment Index="85" Time="3">
    <Info>
      <Scholar Id="0" Type="Scholar">
        <Position>
          <X>95</X>
          <Y>8.450274</Y>
        </Position>
        <Rotation>0</Rotation>
      </Scholar>
    </Info>
  </Moment>
  <Moment Index="86" Time="3">
    <Info>
      <Scholar Id="0" Type="Scholar">
        <Position>
          <X>95</X>
          <Y>8.352174</Y>
        </Position>
        <Rotation>0</Rotation>
      </Scholar>
    </Info>
  </Moment>
  <Moment Index="87" Time="4">
    <Info>
      <Scholar Id="0" Type="Scholar">
        <Position>
          <X>95</X>
          <Y>8.254073</Y>
        </Position>
        <Rotation>0</Rotation>
      </Scholar>
    </Info>
  </Moment>
  <Moment Index="88" Time="4">
    <Info>
      <Scholar Id="0" Type="Scholar">
        <Position>
          <X>95</X>
          <Y>8.15597248</Y>
        </Position>
        <Rotation>0</Rotation>
      </Scholar>
    </Info>
  </Moment>
  <Moment Index="89" Time="4">
    <Info>
      <Scholar Id="0" Type="Scholar">
        <Position>
          <X>95</X>
          <Y>8.00882149</Y>
        </Position>
        <Rotation>0</Rotation>
      </Scholar>
    </Info>
  </Moment>
</Overwatch_Memory_Cell>